setup.cfg
setup.py
tempoiq/__init__.py
tempoiq/client.py
tempoiq/endpoint.py
tempoiq/response.py
tempoiq/session.py
tempoiq/tempo_exceptions.py
tempoiq.egg-info/PKG-INFO
tempoiq.egg-info/SOURCES.txt
tempoiq.egg-info/dependency_links.txt
tempoiq.egg-info/requires.txt
tempoiq.egg-info/top_level.txt
tempoiq/protocol/__init__.py
tempoiq/protocol/cursor.py
tempoiq/protocol/decoder.py
tempoiq/protocol/device.py
tempoiq/protocol/encoder.py
tempoiq/protocol/log.py
tempoiq/protocol/point.py
tempoiq/protocol/row.py
tempoiq/protocol/rule.py
tempoiq/protocol/sensor.py
tempoiq/protocol/stream.py
tempoiq/protocol/query/__init__.py
tempoiq/protocol/query/builder.py
tempoiq/protocol/query/functions.py
tempoiq/protocol/query/pipeline.py
tempoiq/protocol/query/selection.py
tempoiq/temporal/__init__.py
tempoiq/temporal/validate.py