Metadata-Version: 1.0
Name: tempoiq
Version: 1.0.3
Summary: Python bindings for the TempoIQ API
Home-page: http://github.com/tempoiq/tempoiq-python/
Author: TempoIQ Inc
Author-email: aaron.brenzel@tempoiq.com
License: UNKNOWN
Platform: UNKNOWN
